khmerspeech/__init__.py
khmerspeech/_numbers.py
khmerspeech/ascii_lines.py
khmerspeech/cardinals.py
khmerspeech/currency.py
khmerspeech/datetime.py
khmerspeech/decimals.py
khmerspeech/dictionary.py
khmerspeech/hashtags.py
khmerspeech/khmer_dict_verbalize.py
khmerspeech/khmer_license_plate_reorder.py
khmerspeech/khmer_normalize.py
khmerspeech/khmer_number_verbalize.py
khmerspeech/khmer_phonenumbers.py
khmerspeech/khmer_repeater_verbalize.py
khmerspeech/license_plate.py
khmerspeech/normalize.py
khmerspeech/ordinals.py
khmerspeech/parenthesis.py
khmerspeech/phone_numbers.py
khmerspeech/punctuations.py
khmerspeech/quotings.py
khmerspeech/repeater.py
khmerspeech/string_utils.py
khmerspeech/text_url_verbalize.py
khmerspeech/urls.py
khmerspeech/dict/abbreviations_unit.tsv
khmerspeech/dict/autooffice.tsv
khmerspeech/dict/computer_measure_unit.tsv
khmerspeech/dict/lexicon.tsv
khmerspeech/dict/measure_unit.tsv
khmerspeech/dict/spellings.tsv
khmerspeech/dict/verbatim.tsv
khmerspeech-0.1.0.dist-info/licenses/LICENSE
khmerspeech-0.1.0.dist-info/METADATA
khmerspeech-0.1.0.dist-info/WHEEL
khmerspeech-0.1.0.dist-info/top_level.txt
khmerspeech-0.1.0.dist-info/RECORD
