Metadata-Version: 2.4
Name: khmerspeech
Version: 0.1.0
Summary: Add your description here
Home-page: https://github.com/MetythornPenn/khmerspeech
Author: Metythorn Penn
Author-email: metythorn@gmail.com
Requires-Python: >3.8
License-File: LICENSE
Requires-Dist: ftfy>=6.3.1
Requires-Dist: phonenumbers>=9.0.16
Requires-Dist: regex>=2025.9.18
Requires-Dist: urlextract>=1.9.0
Dynamic: author
Dynamic: author-email
Dynamic: home-page
Dynamic: license-file
Dynamic: requires-python
